form_tui/__init__.py
form_tui-0.1.0.dist-info/LICENSE
form_tui-0.1.0.dist-info/METADATA
form_tui-0.1.0.dist-info/WHEEL
form_tui-0.1.0.dist-info/top_level.txt
form_tui-0.1.0.dist-info/RECORD
