Metadata-Version: 2.1
Name: form_tui
Version: 0.1.0
Summary: A simple package for creating TUI forms.
Author-email: Eamon Burns <me@eamonburns.com>
Project-URL: Homepage, https://github.com/agent-e11/form_tui
Project-URL: Issues, https://github.com/agent-e11/form_tui/issues
Classifier: Programming Language :: Python :: 3
Classifier: License :: OSI Approved :: MIT License
Classifier: Operating System :: OS Independent
Requires-Python: >=3.10
License-File: LICENSE
